Metadata-Version: 2.1
Name: DifferentialEquations
Version: 0.0.1
Summary: This library solves differential equations
Home-page: UNKNOWN
Author: ['Alexander Savostianov']
Author-email: s.aleks-02@mail.ru
License: MIT
Platform: UNKNOWN
License-File: LICENSE.txt
